dataclass_args/__init__.py
dataclass_args/annotations.py
dataclass_args/append_action.py
dataclass_args/builder.py
dataclass_args/config_applicator.py
dataclass_args/exceptions.py
dataclass_args/file_loading.py
dataclass_args/formatter.py
dataclass_args/nested_processor.py
dataclass_args/type_inspector.py
dataclass_args/utils.py
dataclass_args-1.4.3.dist-info/licenses/LICENSE
dataclass_args-1.4.3.dist-info/METADATA
dataclass_args-1.4.3.dist-info/WHEEL
dataclass_args-1.4.3.dist-info/top_level.txt
dataclass_args-1.4.3.dist-info/RECORD
