Metadata-Version: 2.4
Name: dataclass-args
Version: 1.4.3
Summary: Zero-boilerplate CLI generation from Python dataclasses with advanced type support and file loading
Author-email: Martin Bartlett <martin.j.bartlett@gmail.com>
License: MIT
Project-URL: Homepage, https://github.com/bassmanitram/dataclass-args
Project-URL: Repository, https://github.com/bassmanitram/dataclass-args
Project-URL: Documentation, https://github.com/bassmanitram/dataclass-args#readme
Project-URL: Issues, https://github.com/bassmanitram/dataclass-args/issues
Keywords: cli,dataclass,argparse,configuration,command-line,type-safe,validation,file-loading,config-merging
Classifier: Development Status :: 5 - Production/Stable
Classifier: Intended Audience :: Developers
Classifier: License :: OSI Approved :: MIT License
Classifier: Operating System :: OS Independent
Classifier: Programming Language :: Python :: 3
Classifier: Programming Language :: Python :: 3.8
Classifier: Programming Language :: Python :: 3.9
Classifier: Programming Language :: Python :: 3.10
Classifier: Programming Language :: Python :: 3.11
Classifier: Programming Language :: Python :: 3.12
Classifier: Topic :: Software Development :: Libraries :: Python Modules
Classifier: Topic :: Software Development :: User Interfaces
Classifier: Topic :: System :: Systems Administration
Classifier: Topic :: Utilities
Requires-Python: >=3.8
License-File: LICENSE
Requires-Dist: typing-extensions>=4.0.0
Provides-Extra: dev
Requires-Dist: pytest>=7.0.0; extra == "dev"
Requires-Dist: pytest-cov>=4.0.0; extra == "dev"
Requires-Dist: black>=23.0.0; extra == "dev"
Requires-Dist: isort>=5.12.0; extra == "dev"
Requires-Dist: mypy>=1.0.0; extra == "dev"
Requires-Dist: pre-commit>=3.0.0; extra == "dev"
Requires-Dist: flake8>=6.0.0; extra == "dev"
Requires-Dist: bandit>=1.7.0; extra == "dev"
Requires-Dist: types-PyYAML>=6.0.0; extra == "dev"
Provides-Extra: yaml
Requires-Dist: PyYAML>=6.0; extra == "yaml"
Provides-Extra: toml
Requires-Dist: tomli>=2.0.0; python_version < "3.11" and extra == "toml"
Provides-Extra: validation
Requires-Dist: pydantic>=2.0; extra == "validation"
Provides-Extra: all
Requires-Dist: dataclass-args[toml,validation,yaml]; extra == "all"
Dynamic: license-file
